metrapy/__init__.py
metrapy/connector.py
metrapy/defaults.py
metrapy/errors.py
metrapy/maps.py
metrapy/sync.py
metrapy/utils.py
metrapy-0.2.1.dist-info/METADATA
metrapy-0.2.1.dist-info/WHEEL
metrapy-0.2.1.dist-info/RECORD
