Metadata-Version: 2.1
Name: metrapy
Version: 0.2.1
Summary: 
Author: pavittarx
Author-email: 29155477+pavittarx@users.noreply.github.com
Requires-Python: >=3.11,<4.0
Classifier: Programming Language :: Python :: 3
Classifier: Programming Language :: Python :: 3.11
Requires-Dist: MetaTrader5 (>=5.0.45,<6.0.0)
Requires-Dist: pandas (>=2.1.4,<3.0.0)
